MANIFEST.in
setup.py
src/ocstyle/__init__.py
src/ocstyle/error.py
src/ocstyle/handlers.py
src/ocstyle/main.py
src/ocstyle/main_test.py
src/ocstyle/rules.py
src/ocstyle/rules_test.py
src/ocstyle.egg-info/PKG-INFO
src/ocstyle.egg-info/SOURCES.txt
src/ocstyle.egg-info/dependency_links.txt
src/ocstyle.egg-info/entry_points.txt
src/ocstyle.egg-info/requires.txt
src/ocstyle.egg-info/top_level.txt
src/ocstyle/testdata/.lintignore
src/ocstyle/testdata/Parsing.h
src/ocstyle/testdata/Parsing.m