Metadata-Version: 1.0
Name: ocstyle
Version: 0.1.1
Summary: Objective-C style checker
Home-page: https://www.github.com/Cue/ocstyle
Author: Cue Technologies, Inc.
Author-email: UNKNOWN
License: UNKNOWN
Platform: UNKNOWN
